robotools/__init__.py
robotools/py.typed
robotools/test_transform.py
robotools/test_utils.py
robotools/test_worklists.py
robotools/transform.py
robotools/utils.py
robotools/evotools/__init__.py
robotools/evotools/commands.py
robotools/evotools/test_commands.py
robotools/evotools/test_utils.py
robotools/evotools/test_worklist.py
robotools/evotools/types.py
robotools/evotools/utils.py
robotools/evotools/worklist.py
robotools/fluenttools/__init__.py
robotools/fluenttools/test_utils.py
robotools/fluenttools/test_worklist.py
robotools/fluenttools/utils.py
robotools/fluenttools/worklist.py
robotools/liquidhandling/__init__.py
robotools/liquidhandling/composition.py
robotools/liquidhandling/exceptions.py
robotools/liquidhandling/labware.py
robotools/liquidhandling/test_composition.py
robotools/liquidhandling/test_labware.py
robotools/worklists/__init__.py
robotools/worklists/base.py
robotools/worklists/exceptions.py
robotools/worklists/test_base.py
robotools/worklists/test_lvh.py
robotools/worklists/test_utils.py
robotools/worklists/utils.py
robotools-1.14.0.dist-info/licenses/LICENSE
robotools-1.14.0.dist-info/METADATA
robotools-1.14.0.dist-info/WHEEL
robotools-1.14.0.dist-info/top_level.txt
robotools-1.14.0.dist-info/RECORD
