Metadata-Version: 2.4
Name: robotools
Version: 1.14.0
Summary: Pythonic in-silico liquid handling and creation of Tecan FreedomEVO worklists.
Author-email: Michael Osthege <m.osthege@fz-juelich.de>
License: GNU Affero General Public License v3
Project-URL: Homepage, https://github.com/jubiotech/robotools
Project-URL: Documentation, https://robotools.readthedocs.io/en/latest/
Project-URL: Download, https://pypi.org/project/robotools/
Classifier: Programming Language :: Python
Classifier: Operating System :: OS Independent
Classifier: Programming Language :: Python :: 3.10
Classifier: Programming Language :: Python :: 3.11
Classifier: Programming Language :: Python :: 3.12
Classifier: License :: OSI Approved :: GNU Affero General Public License v3
Classifier: Intended Audience :: Science/Research
Classifier: Topic :: Scientific/Engineering
Requires-Python: >=3.10
License-File: LICENSE
Requires-Dist: numpy
Requires-Dist: typing_extensions
Dynamic: license-file
